kth_timeoutdecorator/__init__.py
kth_timeoutdecorator/kth_timeoutdecorator.py
kth_timeoutdecorator-0.0.5.dist-info/LICENSE
kth_timeoutdecorator-0.0.5.dist-info/METADATA
kth_timeoutdecorator-0.0.5.dist-info/WHEEL
kth_timeoutdecorator-0.0.5.dist-info/top_level.txt
kth_timeoutdecorator-0.0.5.dist-info/RECORD
