Metadata-Version: 2.1
Name: kth-timeoutdecorator
Version: 0.0.5
Summary: timeout decorator for python
Home-page: https://github.com/Angel-Hair/kth-timeoutdecorator
Author: Angel Hair
Author-email: asdwsl@foxmail.com
License: UNKNOWN
Platform: UNKNOWN
Classifier: Intended Audience :: Developers
Classifier: License :: OSI Approved :: MIT License
Classifier: Operating System :: OS Independent
Classifier: Programming Language :: Python
Classifier: Programming Language :: Python :: 3
Classifier: Programming Language :: Python :: 3.5
Classifier: Programming Language :: Python :: 3.6
Classifier: Programming Language :: Python :: 3.7
Classifier: Programming Language :: Python :: 3.8
Classifier: Topic :: Software Development :: Libraries :: Python Modules
